{"id": "_pytest.helpconfig", "path": "/home/test/Desktop/scrapyio/venv/lib/python3.11/site-packages/_pytest/helpconfig.py", "mtime": 1680855531, "size": 8494, "hash": "ea68cc445dd2a8f8ad4834cc69046ef22cc4419e90d3eece6f64ea3d69027d35", "data_mtime": 1680780743, "dependencies": ["_pytest.config.argparsing", "_pytest.config", "os", "sys", "argparse", "typing", "pytest", "textwrap", "builtins", "_pytest.config.exceptions", "_pytest.hookspec", "_pytest.mark", "_typeshed", "abc", "array", "ctypes", "enum", "io", "mmap", "pickle"], "suppressed": [], "options": {"follow_imports": "normal", "disallow_any_unimported": false, "local_partial_types": false, "always_false": [], "disallow_subclassing_any": false, "disable_bytearray_promotion": false, "allow_redefinition": false, "warn_unreachable": false, "enabled_error_codes": [], "implicit_reexport": true, "platform": "linux", "plugins": [], "disallow_any_expr": false, "disallow_any_generics": false, "disabled_error_codes": [], "strict_equality": false, "disallow_untyped_decorators": false, "check_untyped_defs": false, "implicit_optional": false, "warn_return_any": false, "bazel": false, "always_true": [], "strict_concatenate": false, "enable_error_code": [], "disable_memoryview_promotion": false, "warn_unused_ignores": false, "strict_optional": true, "disable_error_code": [], "disallow_incomplete_defs": false, "follow_imports_for_stubs": false, "allow_untyped_globals": false, "ignore_errors": false, "ignore_missing_imports": true, "mypyc": false, "disallow_untyped_defs": false, "disallow_untyped_calls": true, "disallow_any_decorated": false, "disallow_any_explicit": false, "warn_no_return": false}, "dep_prios": [5, 5, 10, 10, 5, 5, 10, 20, 5, 30, 30, 30, 30, 30, 30, 30, 30, 30, 30, 30], "dep_lines": [13, 10, 2, 3, 4, 5, 9, 160, 1, 1, 1, 1, 1, 1, 1, 1, 1, 1, 1, 1], "interface_hash": "ccdcbf315dfc3a670efb286610edc03c9a2fa74f3d8f83a05670aca788229afe", "version_id": "1.1.1", "ignore_all": true, "plugin_data": null}